setup.py
JRKit/EWMEncoder.py
JRKit/LeaveOneOutEncoder.py
JRKit/RBFEncoder.py
JRKit/RegularizedLinearRegressionEncoder.py
JRKit/__init__.py
JRKit/setup.py
JrKit.egg-info/PKG-INFO
JrKit.egg-info/SOURCES.txt
JrKit.egg-info/dependency_links.txt
JrKit.egg-info/requires.txt
JrKit.egg-info/top_level.txt